[{"legislationRating":"comprehensive legislative framework plus sector specific legislation","code":"AL","sanctionsRating":"light sanctions (fines and other sanctions less than £50,000)","name":"Albania","rating":"Moderate","enforcementRating":"some enforcement (i.e. some enforcement action taken but not regularly adopted)"},{"legislationRating":"comprehensive legislative framework (but no sector specific laws)","code":"DZ","sanctionsRating":"very serious sanctions (imprisonment sanctions and\/or files of £500,000 or more)","name":"Algeria","rating":"Limited","enforcementRating":"no enforcement"},{"legislationRating":"PENDING","code":"AO","sanctionsRating":"PENDING","name":"Angola","rating":"Moderate","enforcementRating":"PENDING"},{"legislationRating":"comprehensive legislative framework (but no sector specific laws)","code":"AR","sanctionsRating":"Other: Fines may not exceed AR $100,000 (around £12,000) but certain actions (such as knowingly inserting in a database or providing false information to a third party, or illegally accessing or disclosing information contained in a database) may be sanctioned with imprisonment (from one month to three years).","name":"Argentina","rating":"Robust","enforcementRating":"some enforcement (i.e. some enforcement action taken but not regularly adopted)"},{"legislationRating":"piecemeal or generic legislation (but no privacy framework or sector specific legislation)","code":"AM","sanctionsRating":"light sanctions (fines and other sanctions less than £50,000)","name":"Armenia","rating":"Limited","enforcementRating":"some enforcement (i.e. some enforcement action taken but not regularly adopted)"},{"legislationRating":"comprehensive legislative framework plus sector specific legislation","code":"AW","sanctionsRating":"very serious sanctions (imprisonment sanctions and\/or files of £500,000 or more)","name":"Aruba","rating":"Robust","enforcementRating":"very strong enforcement (i.e. very regular enforcement action plus imposing &quot;very serious sanctions&quot;)"},{"legislationRating":"comprehensive legislative framework plus sector specific legislation","code":"AU","sanctionsRating":"very serious sanctions (imprisonment sanctions and\/or files of £500,000 or more)","name":"Australia","rating":"Heavy","enforcementRating":"some enforcement (i.e. some enforcement action taken but not regularly adopted)"},{"legislationRating":"comprehensive legislative framework plus sector specific legislation","code":"AT","sanctionsRating":"very serious sanctions (imprisonment sanctions and\/or files of £500,000 or more)","name":"Austria","rating":"Heavy","enforcementRating":"very strong enforcement (i.e. very regular enforcement action plus imposing &quot;very serious sanctions&quot;)"},{"legislationRating":"Other: There is sector specific legislation, but also generic legislation framework (not so comprehensive).","code":"AZ","sanctionsRating":"light sanctions (fines and other sanctions less than £50,000)","name":"Azerbaijan","rating":"Limited","enforcementRating":"some enforcement (i.e. some enforcement action taken but not regularly adopted)"},{"legislationRating":"comprehensive legislative framework (but no sector specific laws)","code":"BS","sanctionsRating":"serious sanctions (fines and other sanctions £50,0000 to £500,000)","name":"Bahamas (the)","rating":"Moderate","enforcementRating":"some enforcement (i.e. some enforcement action taken but not regularly adopted)"},{"legislationRating":"comprehensive legislative framework plus sector specific legislation","code":"BH","sanctionsRating":"very serious sanctions (imprisonment sanctions and\/or files of £500,000 or more)","name":"Bahrain","rating":"Heavy","enforcementRating":"very strong enforcement (i.e. very regular enforcement action plus imposing &quot;very serious sanctions&quot;)"},{"legislationRating":"piecemeal or generic legislation (but no privacy framework or sector specific legislation)","code":"BD","sanctionsRating":"very serious sanctions (imprisonment sanctions and\/or files of £500,000 or more)","name":"Bangladesh","rating":"Limited","enforcementRating":"no enforcement"},{"legislationRating":"comprehensive legislative framework (but no sector specific laws)","code":"BB","sanctionsRating":"serious sanctions (fines and other sanctions £50,0000 to £500,000)","name":"Barbados","rating":"Moderate","enforcementRating":"strong enforcement (i.e. regular enforcement action and &quot;serious sanctions&quot; imposed)"},{"legislationRating":"PENDING","code":"BY","sanctionsRating":"PENDING","name":"Belarus","rating":"Moderate","enforcementRating":"PENDING"},{"legislationRating":"comprehensive legislative framework plus sector specific legislation","code":"BE","sanctionsRating":"very serious sanctions (imprisonment sanctions and\/or files of £500,000 or more)","name":"Belgium","rating":"Heavy","enforcementRating":"very strong enforcement (i.e. very regular enforcement action plus imposing &quot;very serious sanctions&quot;)"},{"legislationRating":"comprehensive legislative framework (but no sector specific laws)","code":"BJ","sanctionsRating":"serious sanctions (fines and other sanctions £50,0000 to £500,000)","name":"Benin","rating":"Moderate","enforcementRating":"some enforcement (i.e. some enforcement action taken but not regularly adopted)"},{"legislationRating":"PENDING","code":"BM","sanctionsRating":"PENDING","name":"Bermuda","rating":"Moderate","enforcementRating":"PENDING"},{"legislationRating":"Other: Bill of Personal Data Protection.","code":"BO","sanctionsRating":"Other: Not specified yet, maybe in the Personal Data Protection Reglament it will be determined.","name":"Bolivia (Plurinational State of)","rating":"Limited","enforcementRating":"Other: Not specified yet, but the Data Authority may distribute enforcement via other organisations in the future."},{"legislationRating":"comprehensive legislative framework plus sector specific legislation","code":"BQ","sanctionsRating":"very serious sanctions (imprisonment sanctions and\/or files of £500,000 or more)","name":"Bonaire, Sint Eustatius and Saba","rating":"Robust","enforcementRating":"strong enforcement (i.e. regular enforcement action and &quot;serious sanctions&quot; imposed)"},{"legislationRating":"PENDING","code":"BA","sanctionsRating":"PENDING","name":"Bosnia and Herzegovina","rating":"Moderate","enforcementRating":"PENDING"},{"legislationRating":"comprehensive legislative framework plus sector specific legislation","code":"BW","sanctionsRating":"serious sanctions (fines and other sanctions £50,0000 to £500,000)","name":"Botswana","rating":"Limited","enforcementRating":"Other: The DPA is still awaiting commencement, thereby rendering the level of enforcement stagnant at this stage."},{"legislationRating":"comprehensive legislative framework plus sector specific legislation","code":"BR","sanctionsRating":"serious sanctions (fines and other sanctions £50,0000 to £500,000)","name":"Brazil","rating":"Moderate","enforcementRating":"Other: "},{"legislationRating":"PENDING","code":"VG","sanctionsRating":"PENDING","name":"British Virgin Islands","rating":"Limited","enforcementRating":"PENDING"},{"legislationRating":"only sector specific legislation","code":"BN","sanctionsRating":"Other: Under section 58 the penalty for breach of confidentiality is up to a maximum of B$150,000 and\/or imprisonment.","name":"Brunei Darussalam","rating":"Limited","enforcementRating":"no enforcement"},{"legislationRating":"comprehensive legislative framework (but no sector specific laws)","code":"BG","sanctionsRating":"very serious sanctions (imprisonment sanctions and\/or files of £500,000 or more)","name":"Bulgaria","rating":"Heavy","enforcementRating":"very strong enforcement (i.e. very regular enforcement action plus imposing &quot;very serious sanctions&quot;)"},{"legislationRating":"comprehensive legislative framework (but no sector specific laws)","code":"BF","sanctionsRating":"serious sanctions (fines and other sanctions £50,0000 to £500,000)","name":"Burkina Faso","rating":"Moderate","enforcementRating":"some enforcement (i.e. some enforcement action taken but not regularly adopted)"},{"legislationRating":"PENDING","code":"BI","sanctionsRating":"PENDING","name":"Burundi","rating":"Limited","enforcementRating":"PENDING"},{"legislationRating":"PENDING","code":"KH","sanctionsRating":"PENDING","name":"Cambodia","rating":"Limited","enforcementRating":"PENDING"},{"legislationRating":"comprehensive legislative framework plus sector specific legislation","code":"CA","sanctionsRating":"Other: Typically non-monetary sanctions (investigations result in recommendations, adverse PR).","name":"Canada","rating":"Heavy","enforcementRating":"Other: Very active enforcement environment."},{"legislationRating":"PENDING","code":"CV","sanctionsRating":"PENDING","name":"Cabo Verde","rating":"Moderate","enforcementRating":"PENDING"},{"legislationRating":"comprehensive legislative framework (but no sector specific laws)","code":"KY","sanctionsRating":"serious sanctions (fines and other sanctions £50,0000 to £500,000)","name":"Cayman Islands","rating":"Moderate","enforcementRating":"some enforcement (i.e. some enforcement action taken but not regularly adopted)"},{"legislationRating":"piecemeal or generic legislation (but no privacy framework or sector specific legislation)","code":"CL","sanctionsRating":"light sanctions (fines and other sanctions less than £50,000)","name":"Chile","rating":"Moderate","enforcementRating":"some enforcement (i.e. some enforcement action taken but not regularly adopted)"},{"legislationRating":"PENDING","code":"TD","sanctionsRating":"PENDING","name":"Chad","rating":"Moderate","enforcementRating":"PENDING"},{"legislationRating":"Other: Piecemeal legislation covering data protection and data security plus sector specific legislation. A multitude of substantial new laws, guidelines, and national standards which touch on data privacy and data security issues have been published. The National People\u2019s Congress (China legislature) has announced that the enactment of a new legislation on data protection and data security is a priority in the next legislative year.","code":"CN","sanctionsRating":"very serious sanctions (imprisonment sanctions and\/or files of £500,000 or more)","name":"China","rating":"Heavy","enforcementRating":"very strong enforcement (i.e. very regular enforcement action plus imposing &quot;very serious sanctions&quot;)"},{"legislationRating":"comprehensive legislative framework plus sector specific legislation","code":"CO","sanctionsRating":"serious sanctions (fines and other sanctions £50,0000 to £500,000)","name":"Colombia","rating":"Moderate","enforcementRating":"some enforcement (i.e. some enforcement action taken but not regularly adopted)"},{"legislationRating":"comprehensive legislative framework (but no sector specific laws)","code":"CR","sanctionsRating":"light sanctions (fines and other sanctions less than £50,000)","name":"Costa Rica","rating":"Moderate","enforcementRating":"some enforcement (i.e. some enforcement action taken but not regularly adopted)"},{"legislationRating":"comprehensive legislative framework plus sector specific legislation","code":"HR","sanctionsRating":"very serious sanctions (imprisonment sanctions and\/or files of £500,000 or more)","name":"Croatia","rating":"Heavy","enforcementRating":"very strong enforcement (i.e. very regular enforcement action plus imposing &quot;very serious sanctions&quot;)"},{"legislationRating":"piecemeal or generic legislation (but no privacy framework or sector specific legislation)","code":"CU","sanctionsRating":"light sanctions (fines and other sanctions less than £50,000)","name":"Cuba","rating":"Limited","enforcementRating":"some enforcement (i.e. some enforcement action taken but not regularly adopted)"},{"legislationRating":"comprehensive legislative framework plus sector specific legislation","code":"CW","sanctionsRating":"very serious sanctions (imprisonment sanctions and\/or files of £500,000 or more)","name":"Curaçao","rating":"Robust","enforcementRating":"strong enforcement (i.e. regular enforcement action and &quot;serious sanctions&quot; imposed)"},{"legislationRating":"comprehensive legislative framework (but no sector specific laws)","code":"CY","sanctionsRating":"Other: Imprisonment sanctions and\/or fines less than £50,000.","name":"Cyprus","rating":"Heavy","enforcementRating":"some enforcement (i.e. some enforcement action taken but not regularly adopted)"},{"legislationRating":"comprehensive legislative framework (but no sector specific laws)","code":"CZ","sanctionsRating":"serious sanctions (fines and other sanctions £50,0000 to £500,000)","name":"Czechia","rating":"Robust","enforcementRating":"strong enforcement (i.e. regular enforcement action and &quot;serious sanctions&quot; imposed)"},{"legislationRating":"PENDING","code":"CD","sanctionsRating":"PENDING","name":"Democratic Republic of the Congo (the)","rating":"Moderate","enforcementRating":"PENDING"},{"legislationRating":"comprehensive legislative framework plus sector specific legislation","code":"DK","sanctionsRating":"very serious sanctions (imprisonment sanctions and\/or files of £500,000 or more)","name":"Denmark","rating":"Heavy","enforcementRating":"very strong enforcement (i.e. very regular enforcement action plus imposing &quot;very serious sanctions&quot;)"},{"legislationRating":"PENDING","code":"DO","sanctionsRating":"PENDING","name":"Dominican Republic (the)","rating":"Moderate","enforcementRating":"PENDING"},{"legislationRating":"comprehensive legislative framework (but no sector specific laws)","code":"EC","sanctionsRating":"serious sanctions (fines and other sanctions £50,0000 to £500,000)","name":"Ecuador","rating":"Moderate","enforcementRating":"no enforcement"},{"legislationRating":"piecemeal or generic legislation (but no privacy framework or sector specific legislation)","code":"EG","sanctionsRating":"very serious sanctions (imprisonment sanctions and\/or files of £500,000 or more)","name":"Egypt","rating":"Robust","enforcementRating":"some enforcement (i.e. some enforcement action taken but not regularly adopted)"},{"legislationRating":"piecemeal or generic legislation (but no privacy framework or sector specific legislation)","code":"SV","sanctionsRating":"Other: Sanctions will depend on the infraction and the legal basis for said infraction. For example, unauthorized transfer of data could be sanctioned with a fine but an infraction considered as a crime could be punished with jail.","name":"El Salvador","rating":"Limited","enforcementRating":"Other: No specific Data Protection Regulation is in place, hence, enforcement is disperse and applicable in relation with the infraction and the legal basis for said infraction."},{"legislationRating":"piecemeal or generic legislation (but no privacy framework or sector specific legislation)","code":"GQ","sanctionsRating":"light sanctions (fines and other sanctions less than £50,000)","name":"Equatorial Guinea","rating":"Limited","enforcementRating":"some enforcement (i.e. some enforcement action taken but not regularly adopted)"},{"legislationRating":"comprehensive legislative framework plus sector specific legislation","code":"EE","sanctionsRating":"very serious sanctions (imprisonment sanctions and\/or files of £500,000 or more)","name":"Estonia","rating":"Heavy","enforcementRating":"very strong enforcement (i.e. very regular enforcement action plus imposing &quot;very serious sanctions&quot;)"},{"legislationRating":"piecemeal or generic legislation (but no privacy framework or sector specific legislation)","code":"ET","sanctionsRating":"very serious sanctions (imprisonment sanctions and\/or files of £500,000 or more)","name":"Ethiopia","rating":"Limited","enforcementRating":"some enforcement (i.e. some enforcement action taken but not regularly adopted)"},{"legislationRating":"PENDING","code":"FJ","sanctionsRating":"PENDING","name":"Fiji","rating":"Limited","enforcementRating":"PENDING"},{"legislationRating":"comprehensive legislative framework plus sector specific legislation","code":"FI","sanctionsRating":"Other: Generally light (guidance, orders, light fines) but in serious cases up to one years imprisonment is possible.","name":"Finland","rating":"Heavy","enforcementRating":"some enforcement (i.e. some enforcement action taken but not regularly adopted)"},{"legislationRating":"comprehensive legislative framework plus sector specific legislation","code":"FR","sanctionsRating":"very serious sanctions (imprisonment sanctions and\/or files of £500,000 or more)","name":"France","rating":"Heavy","enforcementRating":"very strong enforcement (i.e. very regular enforcement action plus imposing &quot;very serious sanctions&quot;)"},{"legislationRating":"comprehensive legislative framework (but no sector specific laws)","code":"GA","sanctionsRating":"serious sanctions (fines and other sanctions £50,0000 to £500,000)","name":"Gabon","rating":"Moderate","enforcementRating":"some enforcement (i.e. some enforcement action taken but not regularly adopted)"},{"legislationRating":"comprehensive legislative framework (but no sector specific laws)","code":"GE","sanctionsRating":"very serious sanctions (imprisonment sanctions and\/or files of £500,000 or more)","name":"Georgia","rating":"Moderate","enforcementRating":"no enforcement"},{"legislationRating":"comprehensive legislative framework plus sector specific legislation","code":"DE","sanctionsRating":"very serious sanctions (imprisonment sanctions and\/or files of £500,000 or more)","name":"Germany","rating":"Heavy","enforcementRating":"very strong enforcement (i.e. very regular enforcement action plus imposing &quot;very serious sanctions&quot;)"},{"legislationRating":"PENDING","code":"GH","sanctionsRating":"PENDING","name":"Ghana","rating":"Moderate","enforcementRating":"PENDING"},{"legislationRating":"comprehensive legislative framework plus sector specific legislation","code":"GI","sanctionsRating":"light sanctions (fines and other sanctions less than £50,000)","name":"Gibraltar","rating":"Moderate","enforcementRating":"some enforcement (i.e. some enforcement action taken but not regularly adopted)"},{"legislationRating":"comprehensive legislative framework plus sector specific legislation","code":"GR","sanctionsRating":"very serious sanctions (imprisonment sanctions and\/or files of £500,000 or more)","name":"Greece","rating":"Heavy","enforcementRating":"very strong enforcement (i.e. very regular enforcement action plus imposing &quot;very serious sanctions&quot;)"},{"legislationRating":"piecemeal or generic legislation (but no privacy framework or sector specific legislation)","code":"GT","sanctionsRating":"Other: It depends on the seriousness of the infraction, as it could be deemed an administrative infraction on public officers, but in case of private parties commercializing personal data sanctions could be prison time and economic fines. However, the amount of the fines should deem such sanctions as light as per the above definition.","name":"Guatemala","rating":"Limited","enforcementRating":"Other: Enforcement varies from the nature of the infraction, as if it is considered an administrative infraction performed by a public officer, the Superior Authorities are competent to enforce administratively from a civil public service standpoint. If the infraction entails a criminal offense, then enforcement is a competence of Prosecutor General\u2019s Office."},{"legislationRating":"PENDING","code":"GG","sanctionsRating":"PENDING","name":"Guernsey","rating":"Moderate","enforcementRating":"PENDING"},{"legislationRating":"PENDING","code":"GN","sanctionsRating":"PENDING","name":"Guinea","rating":"Moderate","enforcementRating":"PENDING"},{"legislationRating":"comprehensive legislative framework (but no sector specific laws)","code":"HT","sanctionsRating":"light sanctions (fines and other sanctions less than £50,000)","name":"Haiti","rating":"Limited","enforcementRating":"some enforcement (i.e. some enforcement action taken but not regularly adopted)"},{"legislationRating":"piecemeal or generic legislation (but no privacy framework or sector specific legislation)","code":"HN","sanctionsRating":"no sanctions","name":"Honduras","rating":"Limited","enforcementRating":"some enforcement (i.e. some enforcement action taken but not regularly adopted)"},{"legislationRating":"comprehensive legislative framework plus sector specific legislation","code":"HK","sanctionsRating":"very serious sanctions (imprisonment sanctions and\/or files of £500,000 or more)","name":"China, Hong Kong Special Administrative Region","rating":"Heavy","enforcementRating":"strong enforcement (i.e. regular enforcement action and &quot;serious sanctions&quot; imposed)"},{"legislationRating":"comprehensive legislative framework plus sector specific legislation","code":"HU","sanctionsRating":"very serious sanctions (imprisonment sanctions and\/or files of £500,000 or more)","name":"Hungary","rating":"Heavy","enforcementRating":"strong enforcement (i.e. regular enforcement action and &quot;serious sanctions&quot; imposed)"},{"legislationRating":"comprehensive legislative framework plus sector specific legislation","code":"IS","sanctionsRating":"very serious sanctions (imprisonment sanctions and\/or files of £500,000 or more)","name":"Iceland","rating":"Heavy","enforcementRating":"very strong enforcement (i.e. very regular enforcement action plus imposing &quot;very serious sanctions&quot;)"},{"legislationRating":"piecemeal or generic legislation (but no privacy framework or sector specific legislation)","code":"IN","sanctionsRating":"serious sanctions (fines and other sanctions £50,0000 to £500,000)","name":"India","rating":"Limited","enforcementRating":"some enforcement (i.e. some enforcement action taken but not regularly adopted)"},{"legislationRating":"only sector specific legislation","code":"ID","sanctionsRating":"light sanctions (fines and other sanctions less than £50,000)","name":"Indonesia","rating":"Limited","enforcementRating":"some enforcement (i.e. some enforcement action taken but not regularly adopted)"},{"legislationRating":"piecemeal or generic legislation (but no privacy framework or sector specific legislation)","code":"IR","sanctionsRating":"very serious sanctions (imprisonment sanctions and\/or files of £500,000 or more)","name":"Iran (Islamic Republic of)","rating":"Limited","enforcementRating":"Other: Judiciary courts entertain claims for breach and violation of personal privacy data and the law enforcement authorities will enforce the verdicts."},{"legislationRating":"comprehensive legislative framework plus sector specific legislation","code":"IE","sanctionsRating":"Other: ","name":"Ireland","rating":"Heavy","enforcementRating":"some enforcement (i.e. some enforcement action taken but not regularly adopted)"},{"legislationRating":"PENDING","code":"IL","sanctionsRating":"PENDING","name":"Israel","rating":"Robust","enforcementRating":"PENDING"},{"legislationRating":"comprehensive legislative framework plus sector specific legislation","code":"IT","sanctionsRating":"very serious sanctions (imprisonment sanctions and\/or files of £500,000 or more)","name":"Italy","rating":"Heavy","enforcementRating":"very strong enforcement (i.e. very regular enforcement action plus imposing &quot;very serious sanctions&quot;)"},{"legislationRating":"comprehensive legislative framework (but no sector specific laws)","code":"JP","sanctionsRating":"very serious sanctions (imprisonment sanctions and\/or files of £500,000 or more)","name":"Japan","rating":"Robust","enforcementRating":"some enforcement (i.e. some enforcement action taken but not regularly adopted)"},{"legislationRating":"PENDING","code":"JE","sanctionsRating":"PENDING","name":"Jersey","rating":"Moderate","enforcementRating":"PENDING"},{"legislationRating":"only sector specific legislation","code":"JO","sanctionsRating":"light sanctions (fines and other sanctions less than £50,000)","name":"Jordan","rating":"Moderate","enforcementRating":"strong enforcement (i.e. regular enforcement action and &quot;serious sanctions&quot; imposed)"},{"legislationRating":"piecemeal or generic legislation (but no privacy framework or sector specific legislation)","code":"KZ","sanctionsRating":"light sanctions (fines and other sanctions less than £50,000)","name":"Kazakhstan","rating":"Limited","enforcementRating":"some enforcement (i.e. some enforcement action taken but not regularly adopted)"},{"legislationRating":"comprehensive legislative framework plus sector specific legislation","code":"KE","sanctionsRating":"light sanctions (fines and other sanctions less than £50,000)","name":"Kenya","rating":"Limited","enforcementRating":"some enforcement (i.e. some enforcement action taken but not regularly adopted)"},{"legislationRating":"comprehensive legislative framework (but no sector specific laws)","code":"XK","sanctionsRating":"serious sanctions (fines and other sanctions £50,0000 to £500,000)","name":"Kosovo (UNSCR 1244)","rating":"Moderate","enforcementRating":"Other: The LPPD provides for enforcement mechanisms. However, due to the fact that LPPD and data protection is an  area in its early stages of development in Kosovo, in practice enforcement may still lack in efficiency."},{"legislationRating":"only sector specific legislation","code":"KW","sanctionsRating":"light sanctions (fines and other sanctions less than £50,000)","name":"Kuwait","rating":"Limited","enforcementRating":"no enforcement"},{"legislationRating":"comprehensive legislative framework (but no sector specific laws)","code":"KG","sanctionsRating":"light sanctions (fines and other sanctions less than £50,000)","name":"Kyrgyzstan","rating":"Limited","enforcementRating":"some enforcement (i.e. some enforcement action taken but not regularly adopted)"},{"legislationRating":"PENDING","code":"LA","sanctionsRating":"PENDING","name":"Lao People's Democratic Republic (the)","rating":"Limited","enforcementRating":"PENDING"},{"legislationRating":"comprehensive legislative framework plus sector specific legislation","code":"LV","sanctionsRating":"light sanctions (fines and other sanctions less than £50,000)","name":"Latvia","rating":"Moderate","enforcementRating":"some enforcement (i.e. some enforcement action taken but not regularly adopted)"},{"legislationRating":"piecemeal or generic legislation (but no privacy framework or sector specific legislation)","code":"LB","sanctionsRating":"light sanctions (fines and other sanctions less than £50,000)","name":"Lebanon","rating":"Limited","enforcementRating":"Other: Yet to be determined in Lebanon."},{"legislationRating":"PENDING","code":"LS","sanctionsRating":"PENDING","name":"Lesotho","rating":"Limited","enforcementRating":"PENDING"},{"legislationRating":"PENDING","code":"LR","sanctionsRating":"PENDING","name":"Liberia","rating":"Limited","enforcementRating":"PENDING"},{"legislationRating":"no legislation","code":"LY","sanctionsRating":"no sanctions","name":"Libya","rating":"Limited","enforcementRating":"no enforcement"},{"legislationRating":"comprehensive legislative framework (but no sector specific laws)","code":"LT","sanctionsRating":"serious sanctions (fines and other sanctions £50,0000 to £500,000)","name":"Lithuania","rating":"Heavy","enforcementRating":"strong enforcement (i.e. regular enforcement action and &quot;serious sanctions&quot; imposed)"},{"legislationRating":"comprehensive legislative framework plus sector specific legislation","code":"LU","sanctionsRating":"serious sanctions (fines and other sanctions £50,0000 to £500,000)","name":"Luxembourg","rating":"Heavy","enforcementRating":"some enforcement (i.e. some enforcement action taken but not regularly adopted)"},{"legislationRating":"PENDING","code":"MO","sanctionsRating":"PENDING","name":"China, Macao Special Administrative Region","rating":"Moderate","enforcementRating":"PENDING"},{"legislationRating":"comprehensive legislative framework plus sector specific legislation","code":"MD","sanctionsRating":"light sanctions (fines and other sanctions less than £50,000)","name":"Republic of Moldova (the)","rating":"Moderate","enforcementRating":"some enforcement (i.e. some enforcement action taken but not regularly adopted)"},{"legislationRating":"Other: The Personal Data Protection Law was adopted by the Parliament of Mongolia on 17 December 2021 which will come into full force from 1 May 2022.","code":"MN","sanctionsRating":"Other: Any breach or violations of the Data Protection Law is subject to sanctions under the Violations Law or the Criminal Code of Mongolia. We cannot insert the level of sanctions given that the relevant amendments have not made yet made to the Violations Law and the Criminal Code following the newly adopted Data Protection Law.","name":"Mongolia","rating":"Limited","enforcementRating":"Other: This remains unknown given that the newly adopted Data Protection Law will come into full force and effect from 1 May 2022. We will be able to provide information about the level of enforcement upon the Data Protection Law came into full force."},{"legislationRating":"PENDING","code":"MK","sanctionsRating":"PENDING","name":"North Macedonia","rating":"Moderate","enforcementRating":"PENDING"},{"legislationRating":"PENDING","code":"MG","sanctionsRating":"PENDING","name":"Madagascar","rating":"Limited","enforcementRating":"PENDING"},{"legislationRating":"comprehensive legislative framework (but no sector specific laws)","code":"MY","sanctionsRating":"very serious sanctions (imprisonment sanctions and\/or files of £500,000 or more)","name":"Malaysia","rating":"Robust","enforcementRating":"no enforcement"},{"legislationRating":"comprehensive legislative framework plus sector specific legislation","code":"MT","sanctionsRating":"very serious sanctions (imprisonment sanctions and\/or files of £500,000 or more)","name":"Malta","rating":"Heavy","enforcementRating":"Other: Strong enforcement (i.e. regular enforcement action but \u201Clight sanctions\u201D)"},{"legislationRating":"comprehensive legislative framework (but no sector specific laws)","code":"MU","sanctionsRating":"light sanctions (fines and other sanctions less than £50,000)","name":"Mauritius","rating":"Moderate","enforcementRating":"some enforcement (i.e. some enforcement action taken but not regularly adopted)"},{"legislationRating":"comprehensive legislative framework (but no sector specific laws)","code":"MX","sanctionsRating":"very serious sanctions (imprisonment sanctions and\/or files of £500,000 or more)","name":"Mexico","rating":"Heavy","enforcementRating":"very strong enforcement (i.e. very regular enforcement action plus imposing &quot;very serious sanctions&quot;)"},{"legislationRating":"comprehensive legislative framework (but no sector specific laws)","code":"MC","sanctionsRating":"serious sanctions (fines and other sanctions £50,0000 to £500,000)","name":"Monaco","rating":"Robust","enforcementRating":"very strong enforcement (i.e. very regular enforcement action plus imposing &quot;very serious sanctions&quot;)"},{"legislationRating":"PENDING","code":"ME","sanctionsRating":"PENDING","name":"Montenegro","rating":"Moderate","enforcementRating":"PENDING"},{"legislationRating":"comprehensive legislative framework plus sector specific legislation","code":"MA","sanctionsRating":"very serious sanctions (imprisonment sanctions and\/or files of £500,000 or more)","name":"Morocco","rating":"Robust","enforcementRating":"no enforcement"},{"legislationRating":"piecemeal or generic legislation (but no privacy framework or sector specific legislation)","code":"MZ","sanctionsRating":"very serious sanctions (imprisonment sanctions and\/or files of £500,000 or more)","name":"Mozambique","rating":"Moderate","enforcementRating":"some enforcement (i.e. some enforcement action taken but not regularly adopted)"},{"legislationRating":"only sector specific legislation","code":"MM","sanctionsRating":"Other: Imprisonment, sanctions and\/or fines of less than GBP 30,000","name":"Myanmar","rating":"Limited","enforcementRating":"Other: No enforcement reported yet"},{"legislationRating":"piecemeal or generic legislation (but no privacy framework or sector specific legislation)","code":"NA","sanctionsRating":"light sanctions (fines and other sanctions less than £50,000)","name":"Namibia","rating":"Limited","enforcementRating":"no enforcement"},{"legislationRating":"piecemeal or generic legislation (but no privacy framework or sector specific legislation)","code":"NP","sanctionsRating":"Other: Imprisonment up to 3 years or fine up to approx. £200 or both.","name":"Nepal","rating":"Limited","enforcementRating":"some enforcement (i.e. some enforcement action taken but not regularly adopted)"},{"legislationRating":"comprehensive legislative framework plus sector specific legislation","code":"NL","sanctionsRating":"very serious sanctions (imprisonment sanctions and\/or files of £500,000 or more)","name":"Netherlands (the)","rating":"Heavy","enforcementRating":"very strong enforcement (i.e. very regular enforcement action plus imposing &quot;very serious sanctions&quot;)"},{"legislationRating":"comprehensive legislative framework plus sector specific legislation","code":"NZ","sanctionsRating":"light sanctions (fines and other sanctions less than £50,000)","name":"New Zealand","rating":"Robust","enforcementRating":"some enforcement (i.e. some enforcement action taken but not regularly adopted)"},{"legislationRating":"comprehensive legislative framework (but no sector specific laws)","code":"NI","sanctionsRating":"Other: The regulation stipulates sanctions, but to date the regulatory body has not been incorporated.","name":"Nicaragua","rating":"Limited","enforcementRating":"no enforcement"},{"legislationRating":"comprehensive legislative framework (but no sector specific laws)","code":"NE","sanctionsRating":"serious sanctions (fines and other sanctions £50,0000 to £500,000)","name":"Niger (the)","rating":"Moderate","enforcementRating":"some enforcement (i.e. some enforcement action taken but not regularly adopted)"},{"legislationRating":"PENDING","code":"NG","sanctionsRating":"PENDING","name":"Nigeria","rating":"Moderate","enforcementRating":"PENDING"},{"legislationRating":"comprehensive legislative framework plus sector specific legislation","code":"NO","sanctionsRating":"very serious sanctions (imprisonment sanctions and\/or files of £500,000 or more)","name":"Norway","rating":"Heavy","enforcementRating":"very strong enforcement (i.e. very regular enforcement action plus imposing &quot;very serious sanctions&quot;)"},{"legislationRating":"no legislation","code":"PK","sanctionsRating":"no sanctions","name":"Pakistan","rating":"Limited","enforcementRating":"no enforcement"},{"legislationRating":"comprehensive legislative framework (but no sector specific laws)","code":"PA","sanctionsRating":"light sanctions (fines and other sanctions less than £50,000)","name":"Panama","rating":"Limited","enforcementRating":"Other: "},{"legislationRating":"piecemeal or generic legislation (but no privacy framework or sector specific legislation)","code":"PY","sanctionsRating":"light sanctions (fines and other sanctions less than £50,000)","name":"Paraguay","rating":"Limited","enforcementRating":"some enforcement (i.e. some enforcement action taken but not regularly adopted)"},{"legislationRating":"comprehensive legislative framework (but no sector specific laws)","code":"PE","sanctionsRating":"Other: Fines range between USD 650 to USD 124,000, approximately, depending on the level of gravity.","name":"Peru","rating":"Moderate","enforcementRating":"Other: For the relatively short time that the regulations have been in place, the authority has been increasing its level of enforcement, approaching to a strong enforcement."},{"legislationRating":"comprehensive legislative framework (but no sector specific laws)","code":"PH","sanctionsRating":"serious sanctions (fines and other sanctions £50,0000 to £500,000)","name":"Philippines (the)","rating":"Moderate","enforcementRating":"some enforcement (i.e. some enforcement action taken but not regularly adopted)"},{"legislationRating":"comprehensive legislative framework plus sector specific legislation","code":"PL","sanctionsRating":"serious sanctions (fines and other sanctions £50,0000 to £500,000)","name":"Poland","rating":"Heavy","enforcementRating":"strong enforcement (i.e. regular enforcement action and &quot;serious sanctions&quot; imposed)"},{"legislationRating":"comprehensive legislative framework plus sector specific legislation","code":"PT","sanctionsRating":"very serious sanctions (imprisonment sanctions and\/or files of £500,000 or more)","name":"Portugal","rating":"Heavy","enforcementRating":"very strong enforcement (i.e. very regular enforcement action plus imposing &quot;very serious sanctions&quot;)"},{"legislationRating":"comprehensive legislative framework plus sector specific legislation","code":"QA","sanctionsRating":"very serious sanctions (imprisonment sanctions and\/or files of £500,000 or more)","name":"Qatar","rating":"Robust","enforcementRating":"Other: "},{"legislationRating":"PENDING","code":"QA2","sanctionsRating":"PENDING","name":"Qatar - Financial Centre","rating":"Moderate","enforcementRating":"PENDING"},{"legislationRating":"PENDING","code":"CG","sanctionsRating":"PENDING","name":"Congo (the)","rating":"Moderate","enforcementRating":"PENDING"},{"legislationRating":"comprehensive legislative framework plus sector specific legislation","code":"RO","sanctionsRating":"very serious sanctions (imprisonment sanctions and\/or files of £500,000 or more)","name":"Romania","rating":"Heavy","enforcementRating":"very strong enforcement (i.e. very regular enforcement action plus imposing &quot;very serious sanctions&quot;)"},{"legislationRating":"comprehensive legislative framework (but no sector specific laws)","code":"RU","sanctionsRating":"light sanctions (fines and other sanctions less than £50,000)","name":"Russian Federation (the)","rating":"Moderate","enforcementRating":"some enforcement (i.e. some enforcement action taken but not regularly adopted)"},{"legislationRating":"comprehensive legislative framework (but no sector specific laws)","code":"RW","sanctionsRating":"very serious sanctions (imprisonment sanctions and\/or files of £500,000 or more)","name":"Rwanda","rating":"Moderate","enforcementRating":"Other: The Data Protection Law has only been in force since October 2021 and DC and DP already in operation have a period of two (2) years since the entry in force to conform to its provisions. It is therefore premature to assess the level of enforcement of the Data Protection Law."},{"legislationRating":"comprehensive legislative framework plus sector specific legislation","code":"SA","sanctionsRating":"Other: There are no penalties specified under the PDPIR.  There are significant sanctions under the PDPL, when it comes into effect.","name":"Saudi Arabia","rating":"Moderate","enforcementRating":"Other: Enforcement actions are not necessarily published or made publicly available, although currently there is no express enforcement mechanism under the PDPIR. The PDPL is not yet in force."},{"legislationRating":"PENDING","code":"SN","sanctionsRating":"PENDING","name":"Senegal","rating":"Robust","enforcementRating":"PENDING"},{"legislationRating":"comprehensive legislative framework plus sector specific legislation","code":"RS","sanctionsRating":"very serious sanctions (imprisonment sanctions and\/or files of £500,000 or more)","name":"Serbia","rating":"Robust","enforcementRating":"some enforcement (i.e. some enforcement action taken but not regularly adopted)"},{"legislationRating":"PENDING","code":"SC","sanctionsRating":"PENDING","name":"Seychelles","rating":"Limited","enforcementRating":"PENDING"},{"legislationRating":"comprehensive legislative framework plus sector specific legislation","code":"SG","sanctionsRating":"very serious sanctions (imprisonment sanctions and\/or files of £500,000 or more)","name":"Singapore","rating":"Heavy","enforcementRating":"Other: None at the moment as the main provisions of the Personal Data Protection Act are not yet in force."},{"legislationRating":"comprehensive legislative framework plus sector specific legislation","code":"SX","sanctionsRating":"very serious sanctions (imprisonment sanctions and\/or files of £500,000 or more)","name":"Sint Maarten (Dutch part)","rating":"Robust","enforcementRating":"strong enforcement (i.e. regular enforcement action and &quot;serious sanctions&quot; imposed)"},{"legislationRating":"comprehensive legislative framework plus sector specific legislation","code":"SK","sanctionsRating":"serious sanctions (fines and other sanctions £50,0000 to £500,000)","name":"Slovakia","rating":"Heavy","enforcementRating":"strong enforcement (i.e. regular enforcement action and &quot;serious sanctions&quot; imposed)"},{"legislationRating":"comprehensive legislative framework plus sector specific legislation","code":"SI","sanctionsRating":"very serious sanctions (imprisonment sanctions and\/or files of £500,000 or more)","name":"Slovenia","rating":"Heavy","enforcementRating":"very strong enforcement (i.e. very regular enforcement action plus imposing &quot;very serious sanctions&quot;)"},{"legislationRating":"comprehensive legislative framework (but no sector specific laws)","code":"ZA","sanctionsRating":"serious sanctions (fines and other sanctions £50,0000 to £500,000)","name":"South Africa","rating":"Moderate","enforcementRating":"Other: "},{"legislationRating":"comprehensive legislative framework plus sector specific legislation","code":"KR","sanctionsRating":"very serious sanctions (imprisonment sanctions and\/or files of £500,000 or more)","name":"Republic of Korea (the)","rating":"Heavy","enforcementRating":"some enforcement (i.e. some enforcement action taken but not regularly adopted)"},{"legislationRating":"comprehensive legislative framework plus sector specific legislation","code":"ES","sanctionsRating":"very serious sanctions (imprisonment sanctions and\/or files of £500,000 or more)","name":"Spain","rating":"Heavy","enforcementRating":"very strong enforcement (i.e. very regular enforcement action plus imposing &quot;very serious sanctions&quot;)"},{"legislationRating":"Other: The bill has been published in the Government Gazette and is to be passed by Parliament in the near future.","code":"LK","sanctionsRating":"light sanctions (fines and other sanctions less than £50,000)","name":"Sri Lanka","rating":"Limited","enforcementRating":"Other: As the legislation is yet to be adopted, the level of enforceability cannot be commented on at this time."},{"legislationRating":"comprehensive legislative framework plus sector specific legislation","code":"SE","sanctionsRating":"Other: Criminal sanctions (fines and imprisonment up to two years) plus damages to data subjects.","name":"Sweden","rating":"Heavy","enforcementRating":"very strong enforcement (i.e. very regular enforcement action plus imposing &quot;very serious sanctions&quot;)"},{"legislationRating":"comprehensive legislative framework (but no sector specific laws)","code":"CH","sanctionsRating":"light sanctions (fines and other sanctions less than £50,000)","name":"Switzerland","rating":"Heavy","enforcementRating":"some enforcement (i.e. some enforcement action taken but not regularly adopted)"},{"legislationRating":"comprehensive legislative framework plus sector specific legislation","code":"TW","sanctionsRating":"serious sanctions (fines and other sanctions £50,0000 to £500,000)","name":"Taiwan","rating":"Robust","enforcementRating":"strong enforcement (i.e. regular enforcement action and &quot;serious sanctions&quot; imposed)"},{"legislationRating":"comprehensive legislative framework plus sector specific legislation","code":"TJ","sanctionsRating":"light sanctions (fines and other sanctions less than £50,000)","name":"Tajikistan","rating":"Moderate","enforcementRating":"strong enforcement (i.e. regular enforcement action and &quot;serious sanctions&quot; imposed)"},{"legislationRating":"PENDING","code":"TZ","sanctionsRating":"PENDING","name":"United Republic of Tanzania (the)","rating":"Limited","enforcementRating":"PENDING"},{"legislationRating":"comprehensive legislative framework (but no sector specific laws)","code":"TH","sanctionsRating":"very serious sanctions (imprisonment sanctions and\/or files of £500,000 or more)","name":"Thailand","rating":"Robust","enforcementRating":"Other: The currently effective PDPA only provides for a legislative framework. The detailed regulations will be prescribed by way of subordinate legislation, which is currently pending. Enforcement hence will be subject to the pending legislation."},{"legislationRating":"no legislation","code":"TO","sanctionsRating":"no sanctions","name":"Tonga","rating":"Limited","enforcementRating":"no enforcement"},{"legislationRating":"piecemeal or generic legislation (but no privacy framework or sector specific legislation)","code":"TT","sanctionsRating":"light sanctions (fines and other sanctions less than £50,000)","name":"Trinidad and Tobago","rating":"Limited","enforcementRating":"no enforcement"},{"legislationRating":"Other: Comprehensive legislative framework plus one sector specific legislation (e-commerce).","code":"TN","sanctionsRating":"very serious sanctions (imprisonment sanctions and\/or files of £500,000 or more)","name":"Tunisia","rating":"Robust","enforcementRating":"some enforcement (i.e. some enforcement action taken but not regularly adopted)"},{"legislationRating":"only sector specific legislation","code":"TR","sanctionsRating":"light sanctions (fines and other sanctions less than £50,000)","name":"Turkey","rating":"Moderate","enforcementRating":"some enforcement (i.e. some enforcement action taken but not regularly adopted)"},{"legislationRating":"PENDING","code":"TM","sanctionsRating":"PENDING","name":"Turkmenistan","rating":"Limited","enforcementRating":"PENDING"},{"legislationRating":"PENDING","code":"AE4","sanctionsRating":"PENDING","name":"UAE - Abu Dhabi Global Market Free Zone","rating":"Robust","enforcementRating":"PENDING"},{"legislationRating":"comprehensive legislative framework (but no sector specific laws)","code":"AE2","sanctionsRating":"serious sanctions (fines and other sanctions £50,0000 to £500,000)","name":"UAE - Dubai (DIFC)","rating":"Robust","enforcementRating":"strong enforcement (i.e. regular enforcement action and &quot;serious sanctions&quot; imposed)"},{"legislationRating":"PENDING","code":"AE3","sanctionsRating":"PENDING","name":"UAE - Dubai Health Care City Free Zone","rating":"Moderate","enforcementRating":"PENDING"},{"legislationRating":"piecemeal or generic legislation (but no privacy framework or sector specific legislation)","code":"AE","sanctionsRating":"very serious sanctions (imprisonment sanctions and\/or files of £500,000 or more)","name":"United Arab Emirates (the)","rating":"Moderate","enforcementRating":"some enforcement (i.e. some enforcement action taken but not regularly adopted)"},{"legislationRating":"comprehensive legislative framework plus sector specific legislation","code":"UG","sanctionsRating":"Other: Ugandan law provides for fines on corporations comprising a percentage of the corporation\u2019s annual gross turnover. Given that gross turnover varies from one corporation to the next, we cannot categorise the sanctions within the criteria above.","name":"Uganda","rating":"Moderate","enforcementRating":"some enforcement (i.e. some enforcement action taken but not regularly adopted)"},{"legislationRating":"PENDING","code":"GB","sanctionsRating":"PENDING","name":"United Kingdom of Great Britain and Northern Ireland (the)","rating":"Heavy","enforcementRating":"PENDING"},{"legislationRating":"comprehensive legislative framework (but no sector specific laws)","code":"UA","sanctionsRating":"Other: Small fines but criminal liability including imprisonment\/limitation of freedom for up to 3 years.","name":"Ukraine","rating":"Moderate","enforcementRating":"some enforcement (i.e. some enforcement action taken but not regularly adopted)"},{"legislationRating":"comprehensive legislative framework plus sector specific legislation","code":"US","sanctionsRating":"very serious sanctions (imprisonment sanctions and\/or files of £500,000 or more)","name":"United States of America (the)","rating":"Heavy","enforcementRating":"very strong enforcement (i.e. very regular enforcement action plus imposing &quot;very serious sanctions&quot;)"},{"legislationRating":"comprehensive legislative framework (but no sector specific laws)","code":"UY","sanctionsRating":"light sanctions (fines and other sanctions less than £50,000)","name":"Uruguay","rating":"Robust","enforcementRating":"some enforcement (i.e. some enforcement action taken but not regularly adopted)"},{"legislationRating":"comprehensive legislative framework plus sector specific legislation","code":"UZ","sanctionsRating":"light sanctions (fines and other sanctions less than £50,000)","name":"Uzbekistan","rating":"Moderate","enforcementRating":"some enforcement (i.e. some enforcement action taken but not regularly adopted)"},{"legislationRating":"piecemeal or generic legislation (but no privacy framework or sector specific legislation)","code":"VE","sanctionsRating":"light sanctions (fines and other sanctions less than £50,000)","name":"Venezuela (Bolivarian Republic of)","rating":"Limited","enforcementRating":"some enforcement (i.e. some enforcement action taken but not regularly adopted)"},{"legislationRating":"comprehensive legislative framework plus sector specific legislation","code":"VN","sanctionsRating":"light sanctions (fines and other sanctions less than £50,000)","name":"Viet Nam","rating":"Moderate","enforcementRating":"some enforcement (i.e. some enforcement action taken but not regularly adopted)"},{"legislationRating":"comprehensive legislative framework (but no sector specific laws)","code":"ZM","sanctionsRating":"very serious sanctions (imprisonment sanctions and\/or files of £500,000 or more)","name":"Zambia","rating":"Moderate","enforcementRating":"Other: The DPA is a new piece of legislation and therefore as at the date of this entry, we are not aware of any enforcement action taken by the Regulator."},{"legislationRating":"comprehensive legislative framework (but no sector specific laws)","code":"ZW","sanctionsRating":"light sanctions (fines and other sanctions less than £50,000)","name":"Zimbabwe","rating":"Moderate","enforcementRating":"some enforcement (i.e. some enforcement action taken but not regularly adopted)"}]